{
  "userInfo": {
    "username": "gurumann",
    "name": "gurumann",
    "bioText": "Guru Mann",
    "profileImage": "https://instagram.fpnq13-3.fna.fbcdn.net/v/t51.2885-19/82438284_2856154237740840_5638052098294677504_n.jpg?_nc_ht=instagram.fpnq13-3.fna.fbcdn.net&_nc_cat=100&_nc_oc=Q6cZ2QHv5pKeR_ChpLL1QvlJPhtpJsqKwPzK6cP4PKMN-SQmctNvEveF9MAAxnFDqy6cOpXOogyZsF8aMnpUaofhtzOx&_nc_ohc=fXy4n-ZaBl8Q7kNvgH8yld0&_nc_gid=-FdKHiqM1BSUKiNsur74rw&edm=AP4sbd4BAAAA&ccb=7-5&oh=00_AYEyGljJbPCYHMdfIcC8LvudY-IF1OKCJAuXw4xl24GSrQ&oe=67E4C09E&_nc_sid=7a9f4b",
    "posts": "1,260 posts",
    "followers": "6.1m followers",
    "following": "26 following",
    "links": [
      "https://about.meta.com/",
      "https://developers.facebook.com/docs/instagram",
      "https://www.threads.net/",
      "https://www.facebook.com/help/instagram/261704639352628",
      "https://www.threads.net/?xmt=AQGz-tp15-6hyGlMr7c9ecviMYwohxsny-efiUSif4w9U5k"
    ]
  },
  "reels": [
    {
      "url": "https://www.instagram.com/gurumann/reel/Cyv0YB_oJt4/",
      "thumbnail": "https://instagram.fpnq13-2.fna.fbcdn.net/v/t51.29350-15/352430439_1397748217682377_7052955630942937541_n.jpg?stp=dst-jpg_e35_tt6&efg=eyJ2ZW5jb2RlX3RhZyI6ImltYWdlX3VybGdlbi4xNDQweDE0NDAuc2RyLmYyOTM1MC5kZWZhdWx0X2ltYWdlIn0&_nc_ht=instagram.fpnq13-2.fna.fbcdn.net&_nc_cat=101&_nc_oc=Q6cZ2QHOg_DNVFofrNjmfymmEJ2_iOzXLPRS04fOo30c6NbX-71TJYyPLyGjfewBqkoJxt8csQYC-hTw1oR0GQk_Ow8v&_nc_ohc=ehqkxwGRA48Q7kNvgFZnM8J&_nc_gid=2KSK-7C-0ZW9iy_eMYqHGQ&edm=ABmJApABAAAA&ccb=7-5&ig_cache_key=MzEyMDM0MjgwMDU4Mjc2MzM1NA%3D%3D.3-ccb7-5&oh=00_AYHCgvsRc_bxE5n6PQWF6ZfYQe4782X9CPAo1IQ6QkqkZg&oe=67E4DE77&_nc_sid=b41fef",
      "videoUrl": "blob:https://www.instagram.com/2ee86935-8fd7-42ad-80b3-217d7446ebae",
      "caption": "",
      "likeCount": "173,704 s",
      "postDate": "2023-12-16T23:32:28.000Z",
      "comments": [
        {
          "username": "Unknown",
          "text": "Edited · 65w",
          "likes": "0"
        },
        {
          "username": "Unknown",
          "text": "❤️❤️",
          "likes": "0"
        },
        {
          "username": "Unknown",
          "text": "😍😍",
          "likes": "0"
        },
        {
          "username": "Unknown",
          "text": "❤️💖",
          "likes": "0"
        },
        {
          "username": "mohit_sonkar_2312",
          "text": "",
          "likes": "0"
        },
        {
          "username": "rohandutta_transformation_spc",
          "text": "",
          "likes": "0"
        },
        {
          "username": "itsakashmukherjee",
          "text": "",
          "likes": "0"
        },
        {
          "username": "Unknown",
          "text": "Love you sir",
          "likes": "0"
        },
        {
          "username": "Unknown",
          "text": "❤️❤️",
          "likes": "0"
        },
        {
          "username": "Unknown",
          "text": "❤️❤️",
          "likes": "0"
        }
      ]
    },
    {
      "url": "https://www.instagram.com/gurumann/reel/CysEsY4J0VF/",
      "thumbnail": "https://instagram.fpnq13-2.fna.fbcdn.net/v/t51.29350-15/352430439_1397748217682377_7052955630942937541_n.jpg?stp=dst-jpg_e35_tt6&efg=eyJ2ZW5jb2RlX3RhZyI6ImltYWdlX3VybGdlbi4xNDQweDE0NDAuc2RyLmYyOTM1MC5kZWZhdWx0X2ltYWdlIn0&_nc_ht=instagram.fpnq13-2.fna.fbcdn.net&_nc_cat=101&_nc_oc=Q6cZ2QEvwfNx_E76g-2D5M1OB0vxf4xoismNrF3JGVowxBaCaxZPT1HYqpknJpZ62P2L1OvNNbYLZ6O4POFPMrIwUwBa&_nc_ohc=ehqkxwGRA48Q7kNvgFZnM8J&_nc_gid=7SuYKTRZaPB75YpeeVK-rA&edm=ABmJApABAAAA&ccb=7-5&ig_cache_key=MzEyMDM0MjgwMDU4Mjc2MzM1NA%3D%3D.3-ccb7-5&oh=00_AYHZvfpfAli2Ya9Htq8zG9UXeAMSlI-CqymuuSpVrVDeiw&oe=67E4DE77&_nc_sid=b41fef",
      "videoUrl": "blob:https://www.instagram.com/4b163d78-4e74-480c-aa9e-1cb76eb9131e",
      "caption": "",
      "likeCount": "200,511 s",
      "postDate": "2023-10-22T05:14:49.000Z",
      "comments": [
        {
          "username": "Unknown",
          "text": "Edited · 73w",
          "likes": "0"
        },
        {
          "username": "Unknown",
          "text": "I wish  your movie may superhit n you become a super star as u already a star..❤️❤️❤️",
          "likes": "0"
        },
        {
          "username": "Unknown",
          "text": "Success is built one rep at a time. Work hard, dream big! 💪",
          "likes": "0"
        },
        {
          "username": "Unknown",
          "text": "🔥🔥🔥",
          "likes": "0"
        },
        {
          "username": "Unknown",
          "text": "1 like",
          "likes": "0"
        },
        {
          "username": "Unknown",
          "text": "Fantastic🔥",
          "likes": "0"
        },
        {
          "username": "Unknown",
          "text": "It gives me motivation to stay on my fitness carrier even now it feels my idea not working but it can be work in future ……..🙌🔥❤️ thank u guru man sir 👏",
          "likes": "0"
        },
        {
          "username": "Unknown",
          "text": "Kindly share movie link plz",
          "likes": "0"
        },
        {
          "username": "Unknown",
          "text": "Lovely pic you ji ❤️❤️❤️❤️❤️",
          "likes": "0"
        },
        {
          "username": "Unknown",
          "text": "Excellent coach",
          "likes": "0"
        }
      ]
    },
    {
      "url": "https://www.instagram.com/gurumann/reel/CyoCRQypDll/",
      "thumbnail": "https://instagram.fpnq13-2.fna.fbcdn.net/v/t51.29350-15/352430439_1397748217682377_7052955630942937541_n.jpg?stp=dst-jpg_e35_tt6&efg=eyJ2ZW5jb2RlX3RhZyI6ImltYWdlX3VybGdlbi4xNDQweDE0NDAuc2RyLmYyOTM1MC5kZWZhdWx0X2ltYWdlIn0&_nc_ht=instagram.fpnq13-2.fna.fbcdn.net&_nc_cat=101&_nc_oc=Q6cZ2QGhORLc6yr-hgUipGBxJD7hM_bbOcJBd1QEbP0iXPd1YFGrJ0mIcDUmbRLtOfwhlyge-LSkXcyD4Hwcafyj56YZ&_nc_ohc=ehqkxwGRA48Q7kNvgFZnM8J&_nc_gid=8Jnvg9uubPusIiheiVUpig&edm=ABmJApABAAAA&ccb=7-5&ig_cache_key=MzEyMDM0MjgwMDU4Mjc2MzM1NA%3D%3D.3-ccb7-5&oh=00_AYGNvidrRBl8hmLu5QSmNSo547dDSAZe1-01J9lKkre5Kg&oe=67E4DE77&_nc_sid=b41fef",
      "videoUrl": "blob:https://www.instagram.com/2888f78c-bf4d-49fe-991b-b207b7d35ca2",
      "caption": "",
      "likeCount": "168,681 s",
      "postDate": "2023-10-20T15:44:43.000Z",
      "comments": [
        {
          "username": "Unknown",
          "text": "Edited · 74w",
          "likes": "0"
        },
        {
          "username": "rizwan_786_n",
          "text": "",
          "likes": "0"
        },
        {
          "username": "rizwan_786_n",
          "text": "",
          "likes": "0"
        },
        {
          "username": "Unknown",
          "text": "Dusra vidhut JAMWAL",
          "likes": "0"
        },
        {
          "username": "Unknown",
          "text": "Nice friend👏👏",
          "likes": "0"
        },
        {
          "username": "Unknown",
          "text": "❤️❤️❤️",
          "likes": "0"
        },
        {
          "username": "Unknown",
          "text": "Punjab",
          "likes": "0"
        },
        {
          "username": "only_harishsharma",
          "text": "",
          "likes": "0"
        },
        {
          "username": "Unknown",
          "text": "❤️❤️🔥",
          "likes": "0"
        },
        {
          "username": "Unknown",
          "text": "Love you sir lots of respect,good luck and dher Sara pyaar my guru .. guru man sir ji🙌🙌🙌🙌🙌🙌🙌🙌🙌🙌❤️❤️❤️❤️",
          "likes": "0"
        }
      ]
    },
    {
      "url": "https://www.instagram.com/gurumann/reel/CykxM4XBPD2/",
      "thumbnail": "https://instagram.fpnq13-6.fna.fbcdn.net/v/t51.2885-15/485452883_18490660717054336_5225505441218345098_n.jpg?stp=dst-jpg_e15_tt6&efg=eyJ2ZW5jb2RlX3RhZyI6ImltYWdlX3VybGdlbi43MjB4OTAwLnNkci5mNzU3NjEuZGVmYXVsdF9jb3Zlcl9mcmFtZSJ9&_nc_ht=instagram.fpnq13-6.fna.fbcdn.net&_nc_cat=104&_nc_oc=Q6cZ2QGFxmTHd7Rb7CGlI2Xbs3cHvsqItlSA8t6DQupCq5F9RgB4oiXWj8elmKQLykQ5rdL8Dt5zHVZ34zKnqI12QK1M&_nc_ohc=WSx0vGjRhjMQ7kNvgFP0P18&_nc_gid=XnEMhrVLRuL7Xm07ifZU5A&edm=ABmJApABAAAA&ccb=7-5&ig_cache_key=MzU5Mzk0MTgwMDEzMTg4MTc3NA%3D%3D.3-ccb7-5&oh=00_AYFObsVLUCLP1GNDZYxGJ47gfX-yHSOMTB21PytJfwfFrA&oe=67E4C695&_nc_sid=b41fef",
      "videoUrl": "blob:https://www.instagram.com/e108680f-3e59-45e1-a1d5-606d9a9f36cd",
      "caption": "",
      "likeCount": "68,691 s",
      "postDate": "2023-10-19T09:01:48.000Z",
      "comments": [
        {
          "username": "zeemusiccompany",
          "text": "",
          "likes": "0"
        },
        {
          "username": "Unknown",
          "text": "Actor ko hire Kiya hai ya bodybuilder ko",
          "likes": "0"
        },
        {
          "username": "fitdara1",
          "text": "",
          "likes": "0"
        },
        {
          "username": "Unknown",
          "text": "🔥🔥",
          "likes": "0"
        },
        {
          "username": "Unknown",
          "text": "Reply",
          "likes": "0"
        },
        {
          "username": "Unknown",
          "text": "Love u bhaji, lots of respect and love ❤️ and many congratulations for the movie",
          "likes": "0"
        },
        {
          "username": "rakesh_sojika",
          "text": "",
          "likes": "0"
        },
        {
          "username": "Unknown",
          "text": "The OG of fitfluencer 🙌",
          "likes": "0"
        },
        {
          "username": "Unknown",
          "text": "🙌",
          "likes": "0"
        },
        {
          "username": "beingsagar1",
          "text": "",
          "likes": "0"
        }
      ]
    },
    {
      "url": "https://www.instagram.com/gurumann/reel/Cyi0U28ptYB/",
      "thumbnail": "https://instagram.fpnq13-2.fna.fbcdn.net/v/t51.29350-15/352430439_1397748217682377_7052955630942937541_n.jpg?stp=dst-jpg_e35_tt6&efg=eyJ2ZW5jb2RlX3RhZyI6ImltYWdlX3VybGdlbi4xNDQweDE0NDAuc2RyLmYyOTM1MC5kZWZhdWx0X2ltYWdlIn0&_nc_ht=instagram.fpnq13-2.fna.fbcdn.net&_nc_cat=101&_nc_oc=Q6cZ2QGRuuw6N0x_exKE4iG8EbA4oEkRmCh7OQDOadSD9sP4n7UfOSHe6o-HO8Qk7qIb4QpfFULDJJxc83HZVrv-iiPM&_nc_ohc=ehqkxwGRA48Q7kNvgFZnM8J&_nc_gid=CajQXLF1tOluTPE4L1-mZg&edm=ABmJApABAAAA&ccb=7-5&ig_cache_key=MzEyMDM0MjgwMDU4Mjc2MzM1NA%3D%3D.3-ccb7-5&oh=00_AYFafzp9oD89npIylEBG27xr-u3o2AS-La3sdpCfO9-J-w&oe=67E4DE77&_nc_sid=b41fef",
      "videoUrl": "blob:https://www.instagram.com/3477561b-405d-4cb7-9339-9f5673a2987d",
      "caption": "",
      "likeCount": "188,973 s",
      "postDate": "2023-10-18T15:01:25.000Z",
      "comments": [
        {
          "username": "Unknown",
          "text": "74w",
          "likes": "0"
        },
        {
          "username": "Unknown",
          "text": "Reply",
          "likes": "0"
        },
        {
          "username": "Unknown",
          "text": "Hhfd🔥",
          "likes": "0"
        },
        {
          "username": "Unknown",
          "text": "🔥🔥",
          "likes": "0"
        },
        {
          "username": "Unknown",
          "text": "❤️❤️❤️🙌",
          "likes": "0"
        },
        {
          "username": "harjitsandhu924",
          "text": "",
          "likes": "0"
        },
        {
          "username": "gudvant_singh",
          "text": "",
          "likes": "0"
        },
        {
          "username": "Unknown",
          "text": "Love you sir",
          "likes": "0"
        },
        {
          "username": "Unknown",
          "text": "👍🏼😀",
          "likes": "0"
        },
        {
          "username": "Unknown",
          "text": "Mission India Fit",
          "likes": "0"
        }
      ]
    }
  ]
}